{
  "Routes": [
    {
      "DownstreamPathTemplate": "/api/kisi/create",
      "DownstreamScheme": "http",
      "DownstreamHostAndPorts": [
        {
          "Host": "localhost",
          "Port": 60000
        }
      ],
      "UpstreamPathTemplate": "/kisi/create",
      "UpstreamHttpMethod": [ "Post" ]
    },
    {
      "DownstreamPathTemplate": "/api/kisi/delete/{id}",
      "DownstreamScheme": "http",
      "DownstreamHostAndPorts": [
        {
          "Host": "localhost",
          "Port": 60000
        }
      ],
      "UpstreamPathTemplate": "/kisi/delete/{id}",
      "UpstreamHttpMethod": [ "Get" ]
    },
    {
      "DownstreamPathTemplate": "/api/kisi/update/{id}",
      "DownstreamScheme": "http",
      "DownstreamHostAndPorts": [
        {
          "Host": "localhost",
          "Port": 60000
        }
      ],
      "UpstreamPathTemplate": "/kisi/update/{id}",
      "UpstreamHttpMethod": [ "Put" ]
    },
    {
      "DownstreamPathTemplate": "/api/kisi/get/{id}",
      "DownstreamScheme": "http",
      "DownstreamHostAndPorts": [
        {
          "Host": "localhost",
          "Port": 60000
        }
      ],
      "UpstreamPathTemplate": "/kisi/get/{id}",
      "UpstreamHttpMethod": [ "Get" ]
    },
    {
      "DownstreamPathTemplate": "/api/kisi/get",
      "DownstreamScheme": "http",
      "DownstreamHostAndPorts": [
        {
          "Host": "localhost",
          "Port": 60000
        }
      ],
      "UpstreamPathTemplate": "/kisi/get",
      "UpstreamHttpMethod": [ "Get" ]
    }
  ],
  "GlobalConfiguration": {
    "BaseUrl": "https://localhost:30000"
  }
}